time_functions/__init__.py
time_functions/__main__.py
time_functions/convertTime.py
time_functions/stress.py
time_functions/cli/__init__.py
time_functions/cli/list.py
time_functions/cli/stress.py
time_functions-2.1.dist-info/LICENSE
time_functions-2.1.dist-info/METADATA
time_functions-2.1.dist-info/WHEEL
time_functions-2.1.dist-info/top_level.txt
time_functions-2.1.dist-info/RECORD
